pygobo/__init__.py
pygobo/__main__.py
pygobo/cypher.py
pygobo/reader.py
pygobo-0.3.1.dist-info/LICENSE
pygobo-0.3.1.dist-info/METADATA
pygobo-0.3.1.dist-info/WHEEL
pygobo-0.3.1.dist-info/top_level.txt
pygobo-0.3.1.dist-info/RECORD
