Metadata-Version: 2.1
Name: pygobo
Version: 0.3.1
Summary: Property Graphs for Open Biological and Biomedical Ontologies
Home-page: https://github.com/alexmilowski/pygobo
Author: Alex Miłowski
Author-email: alex@milowski.com
License: UNKNOWN
Keywords: obo ontology property graph
Platform: UNKNOWN
Classifier: Programming Language :: Python :: 3
Classifier: License :: OSI Approved :: MIT License
Classifier: Operating System :: OS Independent
Requires-Python: >=3.6
Requires-Dist: lark-parser
Requires-Dist: redis
Requires-Dist: redisgraph
